CHANGELOG
LICENSE
MANIFEST.in
README.md
setup.py
lsl_toolkits/__init__.py
lsl_toolkits/PasiImage/PasiImageDB.py
lsl_toolkits/PasiImage/__init__.py
lsl_toolkits_pasiimage.egg-info/PKG-INFO
lsl_toolkits_pasiimage.egg-info/SOURCES.txt
lsl_toolkits_pasiimage.egg-info/dependency_links.txt
lsl_toolkits_pasiimage.egg-info/namespace_packages.txt
lsl_toolkits_pasiimage.egg-info/not-zip-safe
lsl_toolkits_pasiimage.egg-info/requires.txt
lsl_toolkits_pasiimage.egg-info/top_level.txt
scripts/imagePASI.py
scripts/pims2fits.py
scripts/summarizePASIImage.py
tests/__init__.py
tests/test_pims.py
tests/test_scripts.py
tests/data/test.pims