Metadata-Version: 2.1
Name: lsl-toolkits-pasiimage
Version: 0.3.1
Summary: LSL Toolkit for PASI Image Database Files
Home-page: https://fornax.phys.unm.edu/lwa/trac/
Author: Jake Hartman
Author-email: jdowell@unm.edu
License: GPL
Classifier: Development Status :: 5 - Production/Stable
Classifier: Intended Audience :: Developers
Classifier: Intended Audience :: Science/Research
Classifier: License :: OSI Approved :: GNU General Public License (GPL)
Classifier: Topic :: Scientific/Engineering :: Astronomy
Classifier: Programming Language :: Python :: 2
Classifier: Programming Language :: Python :: 2.6
Classifier: Programming Language :: Python :: 2.7
Classifier: Operating System :: MacOS :: MacOS X
Classifier: Operating System :: POSIX :: Linux
Requires-Python: >=2.7
License-File: LICENSE
Requires-Dist: numpy>=1.2
Requires-Dist: lsl<3.0,>=2.0
